{
  "GuideData": {
    "AdsController": 
      {
        "NetworkAds": "facebook",

        "BannerAdmob": "ca-app-pub-3940256099942544/6300978111",
        "InterstitialAdmob": "ca-app-pub-3940256099942544/1033173712",
        "NativeAdmob": "ca-app-pub-3940256099942544/2247696110",

        "BannerFacebook": "IMG_16_9_APP_INSTALL#173186393601951_299214384332484",
        "InterstitialFacebook": "IMG_16_9_APP_INSTALL#173186393601951_288058788781377",
        "NativeFacebook": "IMG_16_9_APP_INSTALL#173186393601951_356298065290782",
        "NativeFacebookSingle": "IMG_16_9_APP_INSTALL#173186393601951_356298065290782",
		
        "ImageBanner": false,
        "ImageBannerImg" : "https://media3.giphy.com/media/igVvRDJ4EbhstQyEKh/giphy.gif",
        "ImageBannerURL" : "https://www.google.com"
		
      },

    "items": [
      {
        "title": "test",
        "image": "https://www.zupimages.net/up/21/39/475o.png",
        "color": "#000000",
        "text_size": "25",
        "isLink": true,
		"link_title": "Get Coins",
		"setLink": "https://www.facebook.com",
        "image_link": "https://www.google.com",
        "text": "test",
        "isNative": false,
		"background": "#00FF00"
      },
      {
        "title": "test",
        "image": "https://www.zupimages.net/up/21/39/475o.png",
        "color": "#000000",
        "text_size": "25",
        "isLink": false,
		"link_title": "",
		"setLink": "",
        "image_link": "",
        "text": "test",
        "isNative": false,
		"background": "#00FF00"
      },
      {
        "title": "test",
        "image": "https://www.zupimages.net/up/21/39/475o.png",
        "color": "#000000",
        "text_size": "25",
        "isLink": false,
		"link_title": "",
		"setLink": "",
        "image_link": "",
        "text": "test",
        "isNative": false,
		"background": "#00FF00"
      },
      {
        "title": "test",
        "image": "https://www.zupimages.net/up/21/39/475o.png",
        "color": "#000000",
        "text_size": "25",
        "isLink": false,
		"link_title": "",
		"setLink": "",
        "image_link": "",
        "text": "test",
        "isNative": false,
		"background": "#00FF00"
      },
      {
        "title": "test",
        "image": "https://www.zupimages.net/up/21/39/475o.png",
        "color": "#000000",
        "text_size": "25",
        "isLink": false,
		"link_title": "",
		"setLink": "",
        "image_link": "",
        "text": "test",
        "isNative": false,
		"background": "#00FF00"
      },
      {
        "title": "test",
        "image": "https://www.zupimages.net/up/21/39/475o.png",
        "color": "#000000",
        "text_size": "25",
        "isLink": false,
		"link_title": "",
		"setLink": "",
        "image_link": "",
        "text": "test.",
        "isNative": false,
		"background": "#00FF00"
      }
    ]

  }
}
